ci/__init__.py
ci/tested_versions_utils.py
lumigo_opentelemetry/VERSION
lumigo_opentelemetry/__init__.py
lumigo_opentelemetry/dependencies/__init__.py
lumigo_opentelemetry/external/__init__.py
lumigo_opentelemetry/external/botocore/__init__.py
lumigo_opentelemetry/external/botocore/package.py
lumigo_opentelemetry/external/botocore/version.py
lumigo_opentelemetry/external/botocore/extensions/__init__.py
lumigo_opentelemetry/external/botocore/extensions/dynamodb.py
lumigo_opentelemetry/external/botocore/extensions/lmbd.py
lumigo_opentelemetry/external/botocore/extensions/sqs.py
lumigo_opentelemetry/external/botocore/extensions/types.py
lumigo_opentelemetry/instrumentations/__init__.py
lumigo_opentelemetry/instrumentations/instrumentation_utils.py
lumigo_opentelemetry/instrumentations/instrumentations.py
lumigo_opentelemetry/instrumentations/agno/__init__.py
lumigo_opentelemetry/instrumentations/boto/__init__.py
lumigo_opentelemetry/instrumentations/botocore/__init__.py
lumigo_opentelemetry/instrumentations/botocore/parsers/__init__.py
lumigo_opentelemetry/instrumentations/django/__init__.py
lumigo_opentelemetry/instrumentations/fastapi/__init__.py
lumigo_opentelemetry/instrumentations/fastapi/parsers/__init__.py
lumigo_opentelemetry/instrumentations/flask/__init__.py
lumigo_opentelemetry/instrumentations/grpcio/__init__.py
lumigo_opentelemetry/instrumentations/grpcio/common.py
lumigo_opentelemetry/instrumentations/grpcio/grpc_instrument_client.py
lumigo_opentelemetry/instrumentations/grpcio/grpc_instrument_server.py
lumigo_opentelemetry/instrumentations/httpx/__init__.py
lumigo_opentelemetry/instrumentations/kafka_python/__init__.py
lumigo_opentelemetry/instrumentations/langchain/__init__.py
lumigo_opentelemetry/instrumentations/pika/__init__.py
lumigo_opentelemetry/instrumentations/psycopg/__init__.py
lumigo_opentelemetry/instrumentations/psycopg/instrumentation.py
lumigo_opentelemetry/instrumentations/psycopg/package.py
lumigo_opentelemetry-1.0.199.dist-info/LICENSE
lumigo_opentelemetry-1.0.199.dist-info/METADATA
lumigo_opentelemetry-1.0.199.dist-info/WHEEL
lumigo_opentelemetry-1.0.199.dist-info/entry_points.txt
lumigo_opentelemetry-1.0.199.dist-info/top_level.txt
lumigo_opentelemetry-1.0.199.dist-info/RECORD
