Metadata-Version: 2.1
Name: lumigo-opentelemetry
Version: 1.0.199
Summary: Lumigo OpenTelemetry Distribution for Python
Home-page: https://github.com/lumigo-io/opentelemetry-python-distro
Author: Lumigo LTD (https://lumigo.io)
Author-email: support@lumigo.io
License: Apache License 2.0
Project-URL: Bug Tracker, https://github.com/lumigo-io/opentelemetry-python-distro/issues
Platform: UNKNOWN
Classifier: License :: OSI Approved :: Apache Software License
Classifier: Operating System :: OS Independent
Classifier: Programming Language :: Python :: 3
Requires-Python: >=3.9
Requires-Dist: asgiref (~=3.0)
Requires-Dist: autowrapt (>=1.0)
Requires-Dist: wrapt (>=1.11.0)
Requires-Dist: lumigo-core (==0.0.16)
Requires-Dist: opentelemetry-api (==1.39.1)
Requires-Dist: opentelemetry-sdk (==1.39.1)
Requires-Dist: opentelemetry-sdk-extension-aws (==2.1.0)
Requires-Dist: opentelemetry-exporter-otlp-proto-http (==1.39.1)
Requires-Dist: opentelemetry-semantic-conventions (==0.60b1)
Requires-Dist: opentelemetry-instrumentation (==0.60b1)
Requires-Dist: opentelemetry-instrumentation-asgi (==0.60b1)
Requires-Dist: opentelemetry-instrumentation-aws-lambda (==0.60b1)
Requires-Dist: opentelemetry-instrumentation-boto (==0.60b1)
Requires-Dist: opentelemetry-instrumentation-fastapi (==0.60b1)
Requires-Dist: opentelemetry-instrumentation-flask (==0.60b1)
Requires-Dist: opentelemetry-instrumentation-grpc (==0.60b1)
Requires-Dist: opentelemetry-instrumentation-kafka-python (==0.60b1)
Requires-Dist: opentelemetry-instrumentation-pika (==0.60b1)
Requires-Dist: opentelemetry-instrumentation-psycopg2 (==0.60b1)
Requires-Dist: opentelemetry-instrumentation-pymongo (==0.60b1)
Requires-Dist: opentelemetry-instrumentation-pymysql (==0.60b1)
Requires-Dist: opentelemetry-instrumentation-requests (==0.60b1)
Requires-Dist: opentelemetry-instrumentation-redis (==0.60b1)
Requires-Dist: opentelemetry-instrumentation-django (==0.60b1)
Requires-Dist: opentelemetry-instrumentation-logging (==0.60b1)
Requires-Dist: opentelemetry-instrumentation-httpx (==0.60b1)
Requires-Dist: opentelemetry-instrumentation-langchain (==0.50.1)
Requires-Dist: openinference-instrumentation-agno (==0.1.25)
Requires-Dist: setuptools (<=80.9.0)
Requires-Dist: typing-extensions (==4.7.1) ; python_version < "3.8"
Requires-Dist: importlib-metadata (==6.7.0) ; python_version < "3.8"
